flake8_require_beartype.py
flake8_require_beartype-0.1.1.dist-info/LICENSE
flake8_require_beartype-0.1.1.dist-info/METADATA
flake8_require_beartype-0.1.1.dist-info/WHEEL
flake8_require_beartype-0.1.1.dist-info/entry_points.txt
flake8_require_beartype-0.1.1.dist-info/top_level.txt
flake8_require_beartype-0.1.1.dist-info/RECORD
